Workbook

Sheet Schedule
A1: Year | B1: Type | C1: Shares | D1: Purchase Price | E1: Vesting Start Date | F1: Vesting Periods | G1: Passed Periods | H1: Vested Shares | I1: Unvested Shares | J1: Gains | K1: Original Purchase Price | L1: Post Vest Value | M1: Vested Value | N1: Exercise Date | O1: Down Payment Shares
A2: 2019 | B2: Purchase | C2: 30000 | D2: 1.5 | E2: 44362 | F2: 6 | G2: =MIN(IF((TODAY()-E2)>0,INT(YEARFRAC(TODAY(),E2)+1),0),F2) -> 5 | H2: =INT((G2/F2)*C2) -> 25000 | I2: =C2-H2 -> 5000 | J2: =(INDEX(Prices!$B$2:$B$100,COUNTA(Prices!$B$2:$B$100))-D2)*H2 -> 90000 | K2: =C2*D2 -> 45000 | L2: =C2*INDEX(Prices!$B$2:$B$100,COUNTA(Prices!$B$2:$B$100)) -> 153000 | M2: =K2+J2 -> 135000 | N2: 43830 | O2: 0
A3: 2019 | B3: Catch-Up | C3: 7200 | D3: 0 | E3: 44362 | F3: 6 | G3: =MIN(IF((TODAY()-E3)>0,INT(YEARFRAC(TODAY(),E3)+1),0),F3) -> 5 | H3: =INT((G3/F3)*C3) -> 6000 | I3: =C3-H3 -> 1200 | J3: =(INDEX(Prices!$B$2:$B$100,COUNTA(Prices!$B$2:$B$100))-D3)*H3 -> 30600 | K3: =C3*D3 -> 0 | L3: =C3*INDEX(Prices!$B$2:$B$100,COUNTA(Prices!$B$2:$B$100)) -> 36720 | M3: =K3+J3 -> 30600 | N3: 43830 | O3: 0
A4: 2020 | B4: Purchase | C4: 50000 | D4: 1.85 | E4: 44727 | F4: 5 | G4: =MIN(IF((TODAY()-E4)>0,INT(YEARFRAC(TODAY(),E4)+1),0),F4) -> 4 | H4: =INT((G4/F4)*C4) -> 40000 | I4: =C4-H4 -> 10000 | J4: =(INDEX(Prices!$B$2:$B$100,COUNTA(Prices!$B$2:$B$100))-D4)*H4 -> 130000 | K4: =C4*D4 -> 92500 | L4: =C4*INDEX(Prices!$B$2:$B$100,COUNTA(Prices!$B$2:$B$100)) -> 255000 | M4: =K4+J4 -> 222500 | N4: 44196 | O4: 0
A5: 2020 | B5: Bonus | C5: 5000 | D5: 0 | E5: 44727 | F5: 4 | G5: =MIN(IF((TODAY()-E5)>0,INT(YEARFRAC(TODAY(),E5)+1),0),F5) -> 4 | H5: =INT((G5/F5)*C5) -> 5000 | I5: =C5-H5 -> 0 | J5: =(INDEX(Prices!$B$2:$B$100,COUNTA(Prices!$B$2:$B$100))-D5)*H5 -> 25500 | K5: =C5*D5 -> 0 | L5: =C5*INDEX(Prices!$B$2:$B$100,COUNTA(Prices!$B$2:$B$100)) -> 25500 | M5: =K5+J5 -> 25500 | N5: 44196 | O5: 0
A6: 2021 | B6: Purchase | C6: 80000 | D6: 2.2 | E6: 45199 | F6: 5 | G6: =MIN(IF((TODAY()-E6)>0,INT(YEARFRAC(TODAY(),E6)+1),0),F6) -> 3 | H6: =INT((G6/F6)*C6) -> 48000 | I6: =C6-H6 -> 32000 | J6: =(INDEX(Prices!$B$2:$B$100,COUNTA(Prices!$B$2:$B$100))-D6)*H6 -> 139200 | K6: =C6*D6 -> 176000 | L6: =C6*INDEX(Prices!$B$2:$B$100,COUNTA(Prices!$B$2:$B$100)) -> 408000 | M6: =K6+J6 -> 315200 | N6: 44561 | O6: 0
A7: 2021 | B7: Bonus | C7: 4000 | D7: 2.2 | E7: 45199 | F7: 3 | G7: =MIN(IF((TODAY()-E7)>0,INT(YEARFRAC(TODAY(),E7)+1),0),F7) -> 3 | H7: =INT((G7/F7)*C7) -> 4000 | I7: =C7-H7 -> 0 | J7: =(INDEX(Prices!$B$2:$B$100,COUNTA(Prices!$B$2:$B$100))-D7)*H7 -> 11600 | K7: =C7*D7 -> 8800 | L7: =C7*INDEX(Prices!$B$2:$B$100,COUNTA(Prices!$B$2:$B$100)) -> 20400 | M7: =K7+J7 -> 20400 | N7: 44561 | O7: 0
A8: 2022 | B8: Purchase | C8: 100000 | D8: 2.75 | E8: 45565 | F8: 4 | G8: =MIN(IF((TODAY()-E8)>0,INT(YEARFRAC(TODAY(),E8)+1),0),F8) -> 2 | H8: =INT((G8/F8)*C8) -> 50000 | I8: =C8-H8 -> 50000 | J8: =(INDEX(Prices!$B$2:$B$100,COUNTA(Prices!$B$2:$B$100))-D8)*H8 -> 117500 | K8: =C8*D8 -> 275000 | L8: =C8*INDEX(Prices!$B$2:$B$100,COUNTA(Prices!$B$2:$B$100)) -> 510000 | M8: =K8+J8 -> 392500 | N8: 44926 | O8: 0
A9: 2022 | B9: Free | C9: 20000 | D9: 0 | E9: 46660 | F9: 1 | G9: =MIN(IF((TODAY()-E9)>0,INT(YEARFRAC(TODAY(),E9)+1),0),F9) -> 0 | H9: =INT((G9/F9)*C9) -> 0 | I9: =C9-H9 -> 20000 | J9: =(INDEX(Prices!$B$2:$B$100,COUNTA(Prices!$B$2:$B$100))-D9)*H9 -> 0 | K9: =C9*D9 -> 0 | L9: =C9*INDEX(Prices!$B$2:$B$100,COUNTA(Prices!$B$2:$B$100)) -> 102000 | M9: =K9+J9 -> 0 | N9: 44926 | O9: 0
A10: 2023 | B10: Purchase | C10: 120000 | D10: 3.1 | E10: 45930 | F10: 4 | G10: =MIN(IF((TODAY()-E10)>0,INT(YEARFRAC(TODAY(),E10)+1),0),F10) -> 1 | H10: =INT((G10/F10)*C10) -> 30000 | I10: =C10-H10 -> 90000 | J10: =(INDEX(Prices!$B$2:$B$100,COUNTA(Prices!$B$2:$B$100))-D10)*H10 -> 60000 | K10: =C10*D10 -> 372000 | L10: =C10*INDEX(Prices!$B$2:$B$100,COUNTA(Prices!$B$2:$B$100)) -> 612000 | M10: =K10+J10 -> 432000 | N10: 45291 | O10: 0
A11: 2023 | B11: Bonus | C11: 3500 | D11: 3.1 | E11: 45930 | F11: 3 | G11: =MIN(IF((TODAY()-E11)>0,INT(YEARFRAC(TODAY(),E11)+1),0),F11) -> 1 | H11: =INT((G11/F11)*C11) -> 1166 | I11: =C11-H11 -> 2334 | J11: =(INDEX(Prices!$B$2:$B$100,COUNTA(Prices!$B$2:$B$100))-D11)*H11 -> 2332 | K11: =C11*D11 -> 10850 | L11: =C11*INDEX(Prices!$B$2:$B$100,COUNTA(Prices!$B$2:$B$100)) -> 17850 | M11: =K11+J11 -> 13182 | N11: 45291 | O11: 0
A12: 2024 | B12: Purchase | C12: 150000 | D12: 3.6 | E12: 46295 | F12: 4 | G12: =MIN(IF((TODAY()-E12)>0,INT(YEARFRAC(TODAY(),E12)+1),0),F12) -> 0 | H12: =INT((G12/F12)*C12) -> 0 | I12: =C12-H12 -> 150000 | J12: =(INDEX(Prices!$B$2:$B$100,COUNTA(Prices!$B$2:$B$100))-D12)*H12 -> 0 | K12: =C12*D12 -> 540000 | L12: =C12*INDEX(Prices!$B$2:$B$100,COUNTA(Prices!$B$2:$B$100)) -> 765000 | M12: =K12+J12 -> 540000 | N12: 45657 | O12: -2000
A13: 2024 | B13: Bonus | C13: 3800 | D13: 3.6 | E13: 46295 | F13: 3 | G13: =MIN(IF((TODAY()-E13)>0,INT(YEARFRAC(TODAY(),E13)+1),0),F13) -> 0 | H13: =INT((G13/F13)*C13) -> 0 | I13: =C13-H13 -> 3800 | J13: =(INDEX(Prices!$B$2:$B$100,COUNTA(Prices!$B$2:$B$100))-D13)*H13 -> 0 | K13: =C13*D13 -> 13680 | L13: =C13*INDEX(Prices!$B$2:$B$100,COUNTA(Prices!$B$2:$B$100)) -> 19380 | M13: =K13+J13 -> 13680 | N13: 45657 | O13: 0

Sheet Loans
A1: Loan number | B1: Grant Year | C1: Type | D1: Loan Type | E1: Loan year | F1: Amount | G1: Interest Rate | H1: Due | I1: Annual Interest
A2: 001001 | B2: 2019 | C2: Purchase | D2: Purchase | E2: 43466 | F2: 45000 | G2: 0.0095 | H2: 46949 | I2: =G2*F2 -> 427.5
A3: 001002 | B3: 2019 | C3: Purchase | D3: Interest | E3: 44197 | F3: 520 | G3: 0.0095 | H3: 46949 | I3: =G3*F3 -> 4.94
A4: 001003 | B4: 2019 | C4: Purchase | D4: Interest | E4: 44562 | F4: 410.5 | G4: 0.02 | H4: 46949 | I4: =G4*F4 -> 8.21
A5: 001004 | B5: 2019 | C5: Purchase | D5: Interest | E5: 44927 | F5: 680 | G5: 0.035 | H5: 46949 | I5: =G5*F5 -> 23.8
A6: 001005 | B6: 2019 | C6: Catch-Up | D6: Tax | E6: 44197 | F6: 1800 | G6: 0.0095 | H6: 46949 | I6: =G6*F6 -> 17.1
A7: 001006 | B7: 2019 | C7: Catch-Up | D7: Tax | E7: 44562 | F7: 1950 | G7: 0.02 | H7: 46949 | I7: =G7*F7 -> 39
A8: 001007 | B8: 2019 | C8: Catch-Up | D8: Tax | E8: 44927 | F8: 2100 | G8: 0.035 | H8: 46949 | I8: =G8*F8 -> 73.5
A9: 002001 | B9: 2020 | C9: Purchase | D9: Purchase | E9: 43831 | F9: 92500 | G9: 0.0095 | H9: 47314 | I9: =G9*F9 -> 878.75
A10: 002002 | B10: 2020 | C10: Purchase | D10: Interest | E10: 44562 | F10: 850 | G10: 0.02 | H10: 47314 | I10: =G10*F10 -> 17
A11: 002003 | B11: 2020 | C11: Purchase | D11: Interest | E11: 44927 | F11: 1100 | G11: 0.035 | H11: 47314 | I11: =G11*F11 -> 38.5
A12: 002004 | B12: 2020 | C12: Bonus | D12: Tax | E12: 44562 | F12: 3200 | G12: 0.0095 | H12: 47314 | I12: =G12*F12 -> 30.4
A13: 002005 | B13: 2020 | C13: Bonus | D13: Tax | E13: 44927 | F13: 3600 | G13: 0.035 | H13: 47314 | I13: =G13*F13 -> 126
... A22: 006001 | B22: 2024 | C22: Purchase | D22: Purchase | E22: 45292 | F22: 540000 | G22: 0.04 | H22: 48760 | I22: =G22*F22 -> 21600

Sheet Prices
A1: Effective Date | B1: Share Price
A2: 43830 | B2: 1.5
A3: 43891 | B3: 1.85
A4: 44256 | B4: 2.2
A5: 44621 | B5: 2.75
A6: 44986 | B6: 3.1
A7: 45352 | B7: 3.6
A8: 45717 | B8: 4.25
A9: 46082 | B9: 5.1

Sheet Events
A1: Event Date | B1: Grant Year | C1: Grant Type | D1: Event Type | E1: Granted Shares | F1: Grant Price | G1: Exercise Price | H1: Vested Shares | I1: Tot Vested Shares | J1: Price Increase | K1: Share Price | L1: Income Gains | M1: Cumulative Income | N1: Vesting Cap Gains | O1: Price Increase Cap Gains | P1: Total Cap Gains | Q1: Cumulative Cap Gains
